README.md
setup.py
curobot/__init__.py
curobot/curobot.py
curobot.egg-info/PKG-INFO
curobot.egg-info/SOURCES.txt
curobot.egg-info/dependency_links.txt
curobot.egg-info/entry_points.txt
curobot.egg-info/requires.txt
curobot.egg-info/top_level.txt