Metadata-Version: 1.0
Name: curobot
Version: 0.1.1
Summary: Curation bot for steem network
Home-page: http://github.com/emre/curobot
Author: emre yilmaz
Author-email: mail@emreyilmaz.me
License: MIT
Platform: UNKNOWN
